{
  "type": "object",
  "properties": {
    "interface": {
      "title": "Interface",
      "type": "string"
    },
    "threshold": {
      "title": "Threshold",
      "type": "number"
    },
    "restart": {
      "title": "Restart",
      "type": "boolean"
    },
    "notificationpath": {
      "title": "Notification path",
      "type": "string"
    }
  },
  "default": { "interface": "n2k-on-ve.can-socket", "threshold": 0, "restart": true, "notificationpath": "notifications.interfacewatchdog" }
}
